pyiec104/__init__.py
pyiec104/iec104api.py
pyiec104/iec104types.py
pyiec104/iec104x64d.dll
pyiec104/iec60870common.py
pyiec104/libx86_x64-iec104.so
pyiec104/structureWithEnums.py
pyiec104/tgtcommon.py
pyiec104/tgtdefines.py
pyiec104/tgterrorcodes.py
pyiec104/tgterrorvalues.py
pyiec104/tgtserialtypes.py
pyiec104/tgttypes.py
pyiec104/tests/iec104clienttest.py
pyiec104/tests/iec104servertest.py
pyiec104-21.6.913.dist-info/LICENSE
pyiec104-21.6.913.dist-info/METADATA
pyiec104-21.6.913.dist-info/WHEEL
pyiec104-21.6.913.dist-info/top_level.txt
pyiec104-21.6.913.dist-info/RECORD
